LICENSE
rich_theme_manager/__init__.py
rich_theme_manager/__main__.py
rich_theme_manager/manager.py
rich_theme_manager/theme.py
rich_theme_manager-0.10.0.dist-info/entry_points.txt
rich_theme_manager-0.10.0.dist-info/LICENSE
rich_theme_manager-0.10.0.dist-info/WHEEL
rich_theme_manager-0.10.0.dist-info/METADATA
rich_theme_manager-0.10.0.dist-info/RECORD
