Metadata-Version: 2.1
Name: rich-theme-manager
Version: 0.10.0
Summary: Manage rich themes for CLI applications
Home-page: https://github.com/RhetTbull/rich_theme_manager
License: MIT
Keywords: rich,cli
Author: Rhet Turnbull
Author-email: rturnbull+git@gmail.com
Requires-Python: >=3.8,<4.0.0
Classifier: Development Status :: 3 - Alpha
Classifier: Environment :: Console
Classifier: Framework :: IPython
Classifier: Intended Audience :: Developers
Classifier: License :: OSI Approved :: MIT License
Classifier: Operating System :: MacOS
Classifier: Operating System :: Microsoft :: Windows
Classifier: Operating System :: POSIX :: Linux
Classifier: Programming Language :: Python :: 3
Classifier: Programming Language :: Python :: 3.10
Classifier: Programming Language :: Python :: 3.8
Classifier: Programming Language :: Python :: 3.9
Requires-Dist: rich (>=11.0)
Project-URL: Repository, https://github.com/RhetTbull/rich_theme_manager
